{
  "tickerInfo": {
    "Symbol": "TSYY",
    "longName": "GraniteShares YieldBOOST TSLA ETF",
    "company": "GraniteShares",
    "frequency": "Weekly",
    "group": "금요일",
    "Update": "2025-07-21 17:07:26 KST",
    "52Week": "$9.20 - $26.15",
    "Volume": "1,210,533",
    "AvgVolume": "223,659",
    "NAV": "$10.68",
    "Yield": "N/A",
    "TotalReturn": "-1964.73%"
  },
  "dividendHistory": [
    {
      "배당락": "25. 12. 26"
    },
    {
      "배당락": "25. 12. 19"
    },
    {
      "배당락": "25. 12. 12"
    },
    {
      "배당락": "25. 12. 05"
    },
    {
      "배당락": "25. 11. 28"
    },
    {
      "배당락": "25. 11. 21"
    },
    {
      "배당락": "25. 11. 14"
    },
    {
      "배당락": "25. 11. 07"
    },
    {
      "배당락": "25. 10. 31"
    },
    {
      "배당락": "25. 10. 24"
    },
    {
      "배당락": "25. 10. 17"
    },
    {
      "배당락": "25. 10. 10"
    },
    {
      "배당락": "25. 10. 03"
    },
    {
      "배당락": "25. 09. 26"
    },
    {
      "배당락": "25. 09. 19"
    },
    {
      "배당락": "25. 09. 12"
    },
    {
      "배당락": "25. 09. 05"
    },
    {
      "배당락": "25. 08. 29"
    },
    {
      "배당락": "25. 08. 22"
    },
    {
      "배당락": "25. 08. 15"
    },
    {
      "배당락": "25. 08. 08"
    },
    {
      "배당락": "25. 08. 01"
    },
    {
      "배당락": "25. 07. 25"
    },
    {
      "배당락": "25. 07. 18",
      "배당금": "$0.2570",
      "전일종가": "$9.61",
      "당일시가": "$9.67",
      "당일종가": "$9.64",
      "익일종가": "$9.64"
    },
    {
      "배당락": "25. 07. 11",
      "배당금": "$0.2420",
      "전일종가": "$9.23",
      "당일종가": "$9.39",
      "당일시가": "$9.16",
      "익일종가": "$9.39"
    },
    {
      "배당락": "25. 07. 03",
      "배당금": "$0.2530",
      "전일종가": "$9.30",
      "당일종가": "$9.27",
      "당일시가": "$9.38",
      "익일종가": "$9.27"
    },
    {
      "배당락": "25. 06. 27",
      "배당금": "$0.3000",
      "전일종가": "$9.52",
      "당일종가": "$9.56",
      "당일시가": "$9.61",
      "익일종가": "$9.56"
    },
    {
      "배당락": "25. 06. 20",
      "배당금": "$0.2980",
      "전일종가": "$9.38",
      "당일종가": "$9.47",
      "당일시가": "$9.59",
      "익일종가": "$9.47"
    },
    {
      "배당락": "25. 06. 13",
      "배당금": "$0.3050",
      "전일종가": "$9.27",
      "당일종가": "$9.34",
      "당일시가": "$9.27",
      "익일종가": "$9.34"
    },
    {
      "배당락": "25. 06. 06",
      "배당금": "$0.3040",
      "전일종가": "$9.00",
      "당일종가": "$9.00",
      "당일시가": "$9.03",
      "익일종가": "$9.00"
    },
    {
      "배당락": "25. 05. 23",
      "배당금": "$1.3870",
      "전일종가": "$9.40",
      "당일종가": "$9.33",
      "당일시가": "$9.35",
      "익일종가": "$9.33"
    },
    {
      "배당락": "25. 04. 25",
      "배당금": "$1.4000",
      "전일종가": "$8.43",
      "당일종가": "$8.48",
      "당일시가": "$8.48",
      "익일종가": "$8.48"
    },
    {
      "배당락": "25. 03. 28",
      "배당금": "$1.5390",
      "전일종가": "$9.01",
      "당일종가": "$9.04",
      "당일시가": "$9.05",
      "익일종가": "$9.04"
    },
    {
      "배당락": "25. 02. 28",
      "배당금": "$2.5430",
      "전일종가": "$11.22",
      "당일종가": "$11.21",
      "당일시가": "$11.31",
      "익일종가": "$11.21"
    },
    {
      "배당락": "25. 01. 24",
      "배당금": "$0.7410",
      "전일종가": "$13.18",
      "당일종가": "$13.21",
      "당일시가": "$13.53",
      "익일종가": "$13.21"
    },
    {
      "배당락": "24. 12. 27",
      "배당금": "$0.0460",
      "전일종가": "$12.78",
      "당일종가": "$12.66",
      "당일시가": "$12.80",
      "익일종가": "$12.66"
    }
  ]
}