{
    "backtestData": [
        {
            "date": "2025-07-22",
            "open": 10055,
            "high": 10100,
            "low": 10020,
            "close": 10070,
            "volume": 761541
        },
        {
            "date": "2025-07-23",
            "open": 10245,
            "high": 10267,
            "low": 10170,
            "close": 10235,
            "volume": 402334
        },
        {
            "date": "2025-07-24",
            "open": 10415,
            "high": 10415,
            "low": 10295,
            "close": 10325,
            "volume": 432531
        },
        {
            "date": "2025-07-25",
            "open": 10285,
            "high": 10295,
            "low": 10225,
            "close": 10290,
            "volume": 285325
        },
        {
            "date": "2025-07-28",
            "open": 10465,
            "high": 10575,
            "low": 10420,
            "close": 10575,
            "volume": 390368
        },
        {
            "date": "2025-07-29",
            "open": 10355,
            "high": 10455,
            "low": 10340,
            "close": 10375,
            "volume": 486079
        },
        {
            "date": "2025-07-30",
            "open": 10150,
            "high": 10155,
            "low": 10000,
            "close": 10050,
            "volume": 342710
        },
        {
            "date": "2025-07-31",
            "open": 10065,
            "high": 10200,
            "low": 10065,
            "close": 10155,
            "volume": 216323
        },
        {
            "date": "2025-08-01",
            "open": 10145,
            "high": 10145,
            "low": 9860,
            "close": 9965,
            "volume": 205233
        },
        {
            "date": "2025-08-04",
            "open": 9955,
            "high": 9955,
            "low": 9700,
            "close": 9775,
            "volume": 245710
        },
        {
            "date": "2025-08-05",
            "open": 10000,
            "high": 10035,
            "low": 9970,
            "close": 10025,
            "volume": 163656
        },
        {
            "date": "2025-08-06",
            "open": 9865,
            "high": 9920,
            "low": 9840,
            "close": 9900,
            "volume": 193304
        },
        {
            "date": "2025-08-07",
            "open": 9650,
            "high": 9752,
            "low": 9635,
            "close": 9650,
            "volume": 384742
        },
        {
            "date": "2025-08-08",
            "open": 9805,
            "high": 9915,
            "low": 9780,
            "close": 9910,
            "volume": 263505
        },
        {
            "date": "2025-08-11",
            "open": 9935,
            "high": 9950,
            "low": 9865,
            "close": 9900,
            "volume": 231524
        },
        {
            "date": "2025-08-12",
            "open": 9920,
            "high": 9920,
            "low": 9850,
            "close": 9870,
            "volume": 139817
        },
        {
            "date": "2025-08-13",
            "open": 10145,
            "high": 10190,
            "low": 10135,
            "close": 10140,
            "volume": 163725
        },
        {
            "date": "2025-08-14",
            "open": 10395,
            "high": 10465,
            "low": 10370,
            "close": 10430,
            "volume": 231186
        },
        {
            "date": "2025-08-18",
            "open": 10710,
            "high": 10745,
            "low": 10665,
            "close": 10720,
            "volume": 330407
        },
        {
            "date": "2025-08-19",
            "open": 10885,
            "high": 10890,
            "low": 10760,
            "close": 10795,
            "volume": 329750
        },
        {
            "date": "2025-08-20",
            "open": 10360,
            "high": 10445,
            "low": 10350,
            "close": 10360,
            "volume": 338704
        },
        {
            "date": "2025-08-21",
            "open": 10405,
            "high": 10525,
            "low": 10395,
            "close": 10510,
            "volume": 186263
        },
        {
            "date": "2025-08-22",
            "open": 10555,
            "high": 10575,
            "low": 10470,
            "close": 10490,
            "volume": 201762
        },
        {
            "date": "2025-08-25",
            "open": 10760,
            "high": 10905,
            "low": 10760,
            "close": 10800,
            "volume": 183608
        },
        {
            "date": "2025-08-26",
            "open": 10580,
            "high": 10580,
            "low": 10470,
            "close": 10545,
            "volume": 200811
        },
        {
            "date": "2025-08-27",
            "open": 10565,
            "high": 10625,
            "low": 10565,
            "close": 10620,
            "volume": 126831
        },
        {
            "date": "2025-08-28",
            "open": 10430,
            "high": 10430,
            "low": 10380,
            "close": 10395,
            "volume": 173274
        },
        {
            "date": "2025-08-29",
            "open": 10450,
            "high": 10452,
            "low": 10405,
            "close": 10450,
            "volume": 131405
        },
        {
            "date": "2025-09-01",
            "open": 10460,
            "high": 10525,
            "low": 10435,
            "close": 10455,
            "volume": 132594
        },
        {
            "date": "2025-09-02",
            "open": 10510,
            "high": 10530,
            "low": 10455,
            "close": 10470,
            "volume": 110022
        },
        {
            "date": "2025-09-03",
            "open": 10550,
            "high": 10645,
            "low": 10550,
            "close": 10610,
            "volume": 123719
        },
        {
            "date": "2025-09-04",
            "open": 10545,
            "high": 10570,
            "low": 10515,
            "close": 10545,
            "volume": 161839
        },
        {
            "date": "2025-09-05",
            "open": 10675,
            "high": 10675,
            "low": 10625,
            "close": 10645,
            "volume": 111129
        },
        {
            "date": "2025-09-08",
            "open": 10810,
            "high": 10832,
            "low": 10780,
            "close": 10820,
            "volume": 178413
        },
        {
            "date": "2025-09-09",
            "open": 10780,
            "high": 10780,
            "low": 10715,
            "close": 10765,
            "volume": 168223
        },
        {
            "date": "2025-09-10",
            "open": 10895,
            "high": 10895,
            "low": 10815,
            "close": 10820,
            "volume": 178329
        },
        {
            "date": "2025-09-11",
            "open": 10590,
            "high": 10670,
            "low": 10590,
            "close": 10670,
            "volume": 206933
        },
        {
            "date": "2025-09-12",
            "open": 11205,
            "high": 11245,
            "low": 11185,
            "close": 11240,
            "volume": 290806
        },
        {
            "date": "2025-09-15",
            "open": 11100,
            "high": 11110,
            "low": 11035,
            "close": 11105,
            "volume": 302639
        },
        {
            "date": "2025-09-16",
            "open": 10950,
            "high": 10950,
            "low": 10895,
            "close": 10930,
            "volume": 326747
        },
        {
            "date": "2025-09-17",
            "open": 10985,
            "high": 10985,
            "low": 10935,
            "close": 10970,
            "volume": 173017
        },
        {
            "date": "2025-09-18",
            "open": 11020,
            "high": 11070,
            "low": 10960,
            "close": 11065,
            "volume": 199959
        },
        {
            "date": "2025-09-19",
            "open": 11175,
            "high": 11185,
            "low": 11125,
            "close": 11165,
            "volume": 172323
        },
        {
            "date": "2025-09-22",
            "open": 11230,
            "high": 11255,
            "low": 11135,
            "close": 11185,
            "volume": 209212
        },
        {
            "date": "2025-09-23",
            "open": 11200,
            "high": 11215,
            "low": 11135,
            "close": 11180,
            "volume": 201857
        },
        {
            "date": "2025-09-24",
            "open": 11060,
            "high": 11065,
            "low": 10990,
            "close": 11050,
            "volume": 182153
        },
        {
            "date": "2025-09-25",
            "open": 10875,
            "high": 10900,
            "low": 10855,
            "close": 10870,
            "volume": 212791
        },
        {
            "date": "2025-09-26",
            "open": 10715,
            "high": 10750,
            "low": 10710,
            "close": 10725,
            "volume": 233304
        },
        {
            "date": "2025-09-29",
            "open": 10890,
            "high": 10890,
            "low": 10805,
            "close": 10835,
            "volume": 197272
        },
        {
            "date": "2025-09-30",
            "open": 10895,
            "high": 10920,
            "low": 10855,
            "close": 10915,
            "volume": 127522
        },
        {
            "date": "2025-10-01",
            "open": 11065,
            "high": 11115,
            "low": 11030,
            "close": 11055,
            "volume": 195043
        },
        {
            "date": "2025-10-02",
            "open": 11570,
            "high": 11635,
            "low": 11565,
            "close": 11600,
            "volume": 278096
        },
        {
            "date": "2025-10-10",
            "open": 12375,
            "high": 12995,
            "low": 12365,
            "close": 12580,
            "volume": 455932
        },
        {
            "date": "2025-10-13",
            "open": 12215,
            "high": 12360,
            "low": 12210,
            "close": 12295,
            "volume": 270980
        },
        {
            "date": "2025-10-14",
            "open": 12210,
            "high": 12295,
            "low": 12035,
            "close": 12105,
            "volume": 328167
        },
        {
            "date": "2025-10-15",
            "open": 12100,
            "high": 12205,
            "low": 12090,
            "close": 12205,
            "volume": 202584
        },
        {
            "date": "2025-10-16",
            "open": 12560,
            "high": 12595,
            "low": 12530,
            "close": 12580,
            "volume": 228950
        },
        {
            "date": "2025-10-17",
            "open": 12350,
            "high": 12350,
            "low": 12225,
            "close": 12225,
            "volume": 223719
        },
        {
            "date": "2025-10-20",
            "open": 12100,
            "high": 12150,
            "low": 12090,
            "close": 12150,
            "volume": 136656
        },
        {
            "date": "2025-10-21",
            "open": 12620,
            "high": 12742,
            "low": 12620,
            "close": 12640,
            "volume": 215421
        }
    ],
    "tickerInfo": {
        "Symbol": "0083S0.KS",
        "koName": "1Q 미국메디컬AI",
        "longName": "1Q 미국메디컬AI",
        "company": null,
        "frequency": null,
        "group": null,
        "underlying": null,
        "market": "KOSPI",
        "currency": "KRW",
        "englishName": "Ubs Hana Asset Management Co Ltd - Hana 1Q U.S. Medical AI ETF",
        "earningsDate": "N/A",
        "enterpriseValue": null,
        "marketCap": null,
        "Volume": 140429,
        "AvgVolume": 243563,
        "sharesOutstanding": null,
        "52Week": "9635.0 - 12995.0",
        "Yield": 0,
        "dividendRate": null,
        "payoutRatio": null,
        "Update": "2025-10-20 11:45:57 KST",
        "changes": {}
    }
}
