{
    "tickerInfo": {
        "Symbol": "SMCC",
        "koName": null,
        "longName": null,
        "company": "Defiance",
        "frequency": "매주",
        "group": "수",
        "underlying": "SMCI",
        "market": "NASDAQ",
        "currency": "USD",
        "englishName": "Defiance Leveraged Long + Income SMCI ETF",
        "earningsDate": "N/A",
        "enterpriseValue": null,
        "marketCap": null,
        "Volume": 6629,
        "AvgVolume": 9179,
        "sharesOutstanding": null,
        "52Week": "16.9 - 29.675",
        "Yield": 0,
        "dividendRate": null,
        "payoutRatio": null,
        "Update": "2025-10-16 14:26:46 KST",
        "changes": {}
    },
    "dividendTotal": 1.893,
    "dividendHistory": [
        {
            "배당락": "25. 12. 31"
        },
        {
            "배당락": "25. 12. 24"
        },
        {
            "배당락": "25. 12. 17"
        },
        {
            "배당락": "25. 12. 10"
        },
        {
            "배당락": "25. 12. 03"
        },
        {
            "배당락": "25. 11. 26"
        },
        {
            "배당락": "25. 11. 19"
        },
        {
            "배당락": "25. 11. 12"
        },
        {
            "배당락": "25. 11. 05"
        },
        {
            "배당락": "25. 10. 29"
        },
        {
            "배당락": "25. 10. 22",
            "전일종가": 24.82390022277832
        },
        {
            "배당락": "25. 10. 15",
            "전일종가": 24.56800079345703,
            "당일시가": 25.010000228881836,
            "당일종가": 24.82390022277832
        },
        {
            "배당락": "25. 10. 08",
            "배당금": 0.523,
            "배당률": 0.0688113413304253,
            "전일종가": 27.514,
            "당일시가": 27.51,
            "당일종가": 29.674999,
            "익일종가": 29.273001
        },
        {
            "배당락": "25. 10. 01",
            "배당금": 0.331,
            "배당률": 0.06053108560646338,
            "전일종가": 22.598,
            "당일시가": 22.632999,
            "당일종가": 25.767,
            "익일종가": 25.559
        },
        {
            "배당락": "25. 09. 24",
            "배당금": 0.34,
            "배당률": 0.04783609796667118,
            "전일종가": 22.275,
            "당일시가": 21.719999,
            "당일종가": 21.534,
            "익일종가": 21.573999
        },
        {
            "배당락": "25. 09. 17",
            "배당금": 0.268,
            "배당률": 0.03416422454370599,
            "전일종가": 20.761999,
            "당일시가": 20.459999,
            "당일종가": 20.461,
            "익일종가": 21.408001
        },
        {
            "배당락": "25. 09. 10",
            "배당금": 0.204,
            "배당률": 0.022012257405515833,
            "전일종가": 19.226,
            "당일시가": 19.58,
            "당일종가": 19.827999,
            "익일종가": 19.976
        },
        {
            "배당락": "25. 09. 03",
            "배당금": 0.227,
            "배당률": 0.012853907134767837,
            "전일종가": 17.877001,
            "당일시가": 17.66,
            "당일종가": 17.152,
            "익일종가": 17.596001
        }
    ],
    "backtestData": {
        "dividends": [
            {
                "date": "2025-09-03",
                "amount": 0.227
            },
            {
                "date": "2025-09-10",
                "amount": 0.204
            },
            {
                "date": "2025-09-17",
                "amount": 0.268
            },
            {
                "date": "2025-09-24",
                "amount": 0.34
            },
            {
                "date": "2025-10-01",
                "amount": 0.331
            },
            {
                "date": "2025-10-08",
                "amount": 0.523
            }
        ],
        "prices": [
            {
                "date": "2025-08-20",
                "open": 18.93000030517578,
                "high": 19.600000381469727,
                "low": 18.93000030517578,
                "close": 19.492000579833984,
                "volume": 700
            },
            {
                "date": "2025-08-21",
                "open": 19.700000762939453,
                "high": 19.700000762939453,
                "low": 18.950000762939453,
                "close": 19.211999893188477,
                "volume": 1400
            },
            {
                "date": "2025-08-22",
                "open": 18.934999465942383,
                "high": 20.569000244140625,
                "low": 18.8799991607666,
                "close": 20.569000244140625,
                "volume": 6100
            },
            {
                "date": "2025-08-25",
                "open": 20.989999771118164,
                "high": 21.44300079345703,
                "low": 20.792999267578125,
                "close": 20.792999267578125,
                "volume": 3500
            },
            {
                "date": "2025-08-26",
                "open": 20.729999542236328,
                "high": 20.996000289916992,
                "low": 20.56999969482422,
                "close": 20.996000289916992,
                "volume": 1300
            },
            {
                "date": "2025-08-27",
                "open": 20.719999313354492,
                "high": 21.39699935913086,
                "low": 20.719999313354492,
                "close": 21.30500030517578,
                "volume": 24800
            },
            {
                "date": "2025-08-28",
                "open": 21.200000762939453,
                "high": 21.360000610351562,
                "low": 20.78499984741211,
                "close": 20.78499984741211,
                "volume": 7200
            },
            {
                "date": "2025-08-29",
                "open": 18.514999389648438,
                "high": 18.989999771118164,
                "low": 18.440000534057617,
                "close": 18.513999938964844,
                "volume": 93000
            },
            {
                "date": "2025-09-02",
                "open": 17.850000381469727,
                "high": 17.87700080871582,
                "low": 17.06999969482422,
                "close": 17.87700080871582,
                "volume": 5500
            },
            {
                "date": "2025-09-03",
                "open": 17.65999984741211,
                "high": 17.65999984741211,
                "low": 16.899999618530273,
                "close": 17.152000427246094,
                "volume": 4100
            },
            {
                "date": "2025-09-04",
                "open": 17,
                "high": 17.59600067138672,
                "low": 17,
                "close": 17.59600067138672,
                "volume": 1300
            },
            {
                "date": "2025-09-05",
                "open": 17.729999542236328,
                "high": 17.729999542236328,
                "low": 16.899999618530273,
                "close": 17.39900016784668,
                "volume": 3400
            },
            {
                "date": "2025-09-08",
                "open": 17.788999557495117,
                "high": 17.788999557495117,
                "low": 17.049999237060547,
                "close": 17.115999221801758,
                "volume": 5500
            },
            {
                "date": "2025-09-09",
                "open": 17.530000686645508,
                "high": 19.22599983215332,
                "low": 17.322999954223633,
                "close": 19.22599983215332,
                "volume": 3900
            },
            {
                "date": "2025-09-10",
                "open": 19.579999923706055,
                "high": 21,
                "low": 19.579999923706055,
                "close": 19.827999114990234,
                "volume": 3300
            },
            {
                "date": "2025-09-11",
                "open": 19.780000686645508,
                "high": 20.149999618530273,
                "low": 19.68000030517578,
                "close": 19.97599983215332,
                "volume": 2400
            },
            {
                "date": "2025-09-12",
                "open": 21.889999389648438,
                "high": 21.94499969482422,
                "low": 20.80699920654297,
                "close": 20.80699920654297,
                "volume": 4000
            },
            {
                "date": "2025-09-15",
                "open": 20.649999618530273,
                "high": 21.354999542236328,
                "low": 20.610000610351562,
                "close": 21.125999450683594,
                "volume": 5100
            },
            {
                "date": "2025-09-16",
                "open": 20.559999465942383,
                "high": 20.80900001525879,
                "low": 20.40999984741211,
                "close": 20.761999130249023,
                "volume": 6200
            },
            {
                "date": "2025-09-17",
                "open": 20.459999084472656,
                "high": 20.6299991607666,
                "low": 19.700000762939453,
                "close": 20.461000442504883,
                "volume": 2600
            },
            {
                "date": "2025-09-18",
                "open": 20.56999969482422,
                "high": 21.48900032043457,
                "low": 20.56999969482422,
                "close": 21.408000946044922,
                "volume": 2900
            },
            {
                "date": "2025-09-19",
                "open": 21.791000366210938,
                "high": 21.791000366210938,
                "low": 21.219999313354492,
                "close": 21.469999313354492,
                "volume": 4800
            },
            {
                "date": "2025-09-22",
                "open": 21.950000762939453,
                "high": 23.290000915527344,
                "low": 21.719999313354492,
                "close": 22.136999130249023,
                "volume": 5500
            },
            {
                "date": "2025-09-23",
                "open": 22.208999633789062,
                "high": 22.72100067138672,
                "low": 21.56999969482422,
                "close": 22.274999618530273,
                "volume": 17500
            },
            {
                "date": "2025-09-24",
                "open": 21.719999313354492,
                "high": 22.440000534057617,
                "low": 21.534000396728516,
                "close": 21.534000396728516,
                "volume": 7400
            },
            {
                "date": "2025-09-25",
                "open": 20.06999969482422,
                "high": 22.09000015258789,
                "low": 19.972000122070312,
                "close": 21.573999404907227,
                "volume": 5400
            },
            {
                "date": "2025-09-26",
                "open": 21.190000534057617,
                "high": 21.4060001373291,
                "low": 20.100000381469727,
                "close": 21.4060001373291,
                "volume": 9000
            },
            {
                "date": "2025-09-29",
                "open": 21.540000915527344,
                "high": 22.089000701904297,
                "low": 21.299999237060547,
                "close": 21.535999298095703,
                "volume": 5800
            },
            {
                "date": "2025-09-30",
                "open": 21.690000534057617,
                "high": 22.597999572753906,
                "low": 21.690000534057617,
                "close": 22.597999572753906,
                "volume": 6900
            },
            {
                "date": "2025-10-01",
                "open": 22.632999420166016,
                "high": 25.767000198364258,
                "low": 22.632999420166016,
                "close": 25.767000198364258,
                "volume": 4200
            },
            {
                "date": "2025-10-02",
                "open": 25.400999069213867,
                "high": 25.55900001525879,
                "low": 24.954999923706055,
                "close": 25.55900001525879,
                "volume": 5600
            },
            {
                "date": "2025-10-03",
                "open": 25.722000122070312,
                "high": 25.722000122070312,
                "low": 24.959999084472656,
                "close": 25.25200080871582,
                "volume": 4800
            },
            {
                "date": "2025-10-06",
                "open": 27,
                "high": 27.86199951171875,
                "low": 26.915000915527344,
                "close": 27.17799949645996,
                "volume": 4900
            },
            {
                "date": "2025-10-07",
                "open": 28.639999389648438,
                "high": 29.270000457763672,
                "low": 26.5,
                "close": 27.513999938964844,
                "volume": 20300
            },
            {
                "date": "2025-10-08",
                "open": 27.510000228881836,
                "high": 29.674999237060547,
                "low": 26.8700008392334,
                "close": 29.674999237060547,
                "volume": 24600
            },
            {
                "date": "2025-10-09",
                "open": 28.739999771118164,
                "high": 29.600000381469727,
                "low": 28.739999771118164,
                "close": 29.273000717163086,
                "volume": 4100
            },
            {
                "date": "2025-10-10",
                "open": 29.170000076293945,
                "high": 29.170000076293945,
                "low": 24.3700008392334,
                "close": 24.38599967956543,
                "volume": 11900
            },
            {
                "date": "2025-10-13",
                "open": 25.65999984741211,
                "high": 26.350000381469727,
                "low": 25.38599967956543,
                "close": 26.014999389648438,
                "volume": 13400
            },
            {
                "date": "2025-10-14",
                "open": 25.639999389648438,
                "high": 26,
                "low": 24.559999465942383,
                "close": 24.56800079345703,
                "volume": 13700
            },
            {
                "date": "2025-10-15",
                "open": 25.010000228881836,
                "high": 25.242300033569336,
                "low": 24.09000015258789,
                "close": 24.82390022277832,
                "volume": 6629
            }
        ]
    }
}
