[
  {
    "symbol": "A",
    "market": "NYSE",
    "currency": "USD",
    "ipoDate": "1999-11-18",
    "frequency": "분기",
    "group": "AJSD"
  },
  {
    "symbol": "AAAU",
    "market": "NYSE",
    "currency": "USD",
    "company": "Goldman"
  },
  {
    "symbol": "AAXJ",
    "market": "NYSE",
    "currency": "USD",
    "company": "iShares"
  },
  {
    "symbol": "ABBV",
    "frequency": "분기",
    "group": "JAJO",
    "ipoDate": "2013-01-02",
    "market": "NYSE"
  },
  {
    "symbol": "ABNY",
    "company": "YieldMax",
    "frequency": "매주",
    "group": "목",
    "underlying": "ABNB",
    "ipoDate": "2024-06-25",
    "market": "NYSE"
  },
  {
    "symbol": "ABT",
    "market": "NYSE",
    "currency": "USD",
    "ipoDate": "1980-03-17",
    "frequency": "분기",
    "group": "JAJO"
  },
  {
    "symbol": "ACIO",
    "market": "NYSE",
    "currency": "USD",
    "company": "Aptus"
  },
  {
    "symbol": "ACN",
    "market": "NYSE",
    "currency": "USD",
    "ipoDate": "2001-07-19",
    "frequency": "분기",
    "group": "JAJO"
  },
  {
    "symbol": "ACWI",
    "market": "NYSE",
    "currency": "USD",
    "company": "iShares"
  },
  {
    "symbol": "ACWV",
    "market": "NYSE",
    "currency": "USD",
    "company": "iShares"
  },
  {
    "symbol": "ACWX",
    "market": "NYSE",
    "currency": "USD",
    "company": "iShares"
  },
  {
    "symbol": "ADM",
    "market": "NYSE",
    "currency": "USD",
    "ipoDate": "1980-03-17",
    "frequency": "분기",
    "group": "FMAN"
  },
  {
    "symbol": "AEE",
    "market": "NYSE",
    "currency": "USD",
    "ipoDate": "1998-01-02",
    "frequency": "분기",
    "group": "MJSD"
  },
  {
    "symbol": "AES",
    "market": "NYSE",
    "currency": "USD",
    "ipoDate": "1991-06-26",
    "frequency": "분기",
    "group": "JMAN"
  },
  {
    "symbol": "AFL",
    "market": "NYSE",
    "currency": "USD",
    "ipoDate": "1980-03-17",
    "frequency": "분기",
    "group": "FMAN"
  },
  {
    "symbol": "AGG",
    "market": "NYSE",
    "currency": "USD",
    "company": "iShares"
  },
  {
    "symbol": "AGGY",
    "market": "NYSE",
    "currency": "USD",
    "company": "WisdomTree"
  },
  {
    "symbol": "AGQ",
    "market": "NYSE",
    "currency": "USD",
    "company": "ProShares"
  },
  {
    "symbol": "AI",
    "ipoDate": "2020-12-09",
    "market": "NYSE"
  },
  {
    "symbol": "AIA",
    "market": "NYSE",
    "currency": "USD",
    "company": "iShares"
  },
  {
    "symbol": "AIG",
    "market": "NYSE",
    "currency": "USD",
    "ipoDate": "1973-01-02",
    "frequency": "분기",
    "group": "MJSD"
  },
  {
    "symbol": "AIQ",
    "market": "NYSE",
    "currency": "USD",
    "company": "Global"
  },
  {
    "symbol": "AIRR",
    "market": "NYSE",
    "currency": "USD",
    "company": "First"
  },
  {
    "symbol": "AIYY",
    "company": "YieldMax",
    "frequency": "매주",
    "group": "목",
    "underlying": "AI",
    "ipoDate": "2023-11-28",
    "market": "NYSE"
  },
  {
    "symbol": "AIZ",
    "market": "NYSE",
    "currency": "USD",
    "ipoDate": "2004-02-05",
    "frequency": "분기",
    "group": "FJSD"
  },
  {
    "symbol": "AJG",
    "market": "NYSE",
    "currency": "USD",
    "ipoDate": "1984-06-20",
    "frequency": "분기",
    "group": "MJSD"
  },
  {
    "symbol": "ALB",
    "market": "NYSE",
    "currency": "USD",
    "ipoDate": "1994-02-22",
    "frequency": "분기",
    "group": "MJSD"
  },
  {
    "symbol": "ALL",
    "market": "NYSE",
    "currency": "USD",
    "ipoDate": "1993-06-03",
    "frequency": "분기",
    "group": "MJAN"
  },
  {
    "symbol": "ALLE",
    "market": "NYSE",
    "currency": "USD",
    "ipoDate": "2013-11-18",
    "frequency": "분기",
    "group": "MJSD"
  },
  {
    "symbol": "AMCR",
    "market": "NYSE",
    "currency": "USD",
    "ipoDate": "2012-05-15",
    "frequency": "분기",
    "group": "FMSN"
  },
  {
    "symbol": "AMDL",
    "market": "NYSE",
    "currency": "USD",
    "company": "GraniteShares"
  },
  {
    "symbol": "AMDY",
    "company": "YieldMax",
    "frequency": "매주",
    "group": "목",
    "underlying": "AMD",
    "ipoDate": "2023-09-19",
    "market": "NYSE"
  },
  {
    "symbol": "AME",
    "market": "NYSE",
    "currency": "USD",
    "ipoDate": "1984-07-19",
    "frequency": "분기",
    "group": "MJSD"
  },
  {
    "symbol": "AMLP",
    "market": "NYSE",
    "currency": "USD",
    "company": "Alerian"
  },
  {
    "symbol": "AMP",
    "market": "NYSE",
    "currency": "USD",
    "ipoDate": "2005-09-15",
    "frequency": "분기",
    "group": "FMAN"
  },
  {
    "symbol": "AMT",
    "market": "NYSE",
    "currency": "USD",
    "ipoDate": "1998-02-27",
    "frequency": "분기",
    "group": "AJSD"
  },
  {
    "symbol": "AMZY",
    "company": "YieldMax",
    "frequency": "매주",
    "group": "목",
    "underlying": "AMZN",
    "ipoDate": "2023-07-25",
    "market": "NYSE"
  },
  {
    "symbol": "ANET",
    "market": "NYSE",
    "currency": "USD",
    "ipoDate": "2014-06-06"
  },
  {
    "symbol": "ANGL",
    "market": "NYSE",
    "currency": "USD",
    "company": "VanEck"
  },
  {
    "symbol": "AOA",
    "market": "NYSE",
    "currency": "USD",
    "company": "iShares"
  },
  {
    "symbol": "AOM",
    "market": "NYSE",
    "currency": "USD",
    "company": "iShares"
  },
  {
    "symbol": "AON",
    "market": "NYSE",
    "currency": "USD",
    "ipoDate": "1980-06-02",
    "frequency": "분기",
    "group": "FMAN"
  },
  {
    "symbol": "AOR",
    "market": "NYSE",
    "currency": "USD",
    "company": "iShares"
  },
  {
    "symbol": "AOS",
    "market": "NYSE",
    "currency": "USD",
    "ipoDate": "1983-09-30",
    "frequency": "분기",
    "group": "JAJO"
  },
  {
    "symbol": "APCB",
    "market": "NYSE",
    "currency": "USD",
    "company": "ActivePassive"
  },
  {
    "symbol": "APD",
    "market": "NYSE",
    "currency": "USD",
    "ipoDate": "1980-03-17",
    "frequency": "분기",
    "group": "JAJO"
  },
  {
    "symbol": "APH",
    "market": "NYSE",
    "currency": "USD",
    "ipoDate": "1991-11-08",
    "frequency": "분기",
    "group": "MJSD"
  },
  {
    "symbol": "APIE",
    "market": "NYSE",
    "currency": "USD",
    "company": "ActivePassive"
  },
  {
    "symbol": "APLY",
    "company": "YieldMax",
    "frequency": "매주",
    "group": "목",
    "underlying": "AAPL",
    "ipoDate": "2023-04-18",
    "market": "NYSE"
  },
  {
    "symbol": "APO",
    "market": "NYSE",
    "currency": "USD",
    "ipoDate": "2011-03-30",
    "frequency": "분기",
    "group": "FMAN"
  },
  {
    "symbol": "APTV",
    "market": "NYSE",
    "currency": "USD",
    "ipoDate": "2011-11-17",
    "frequency": "분기",
    "group": "FMAN"
  },
  {
    "symbol": "APUE",
    "market": "NYSE",
    "currency": "USD",
    "company": "ActivePassive"
  },
  {
    "symbol": "ARE",
    "market": "NYSE",
    "currency": "USD",
    "ipoDate": "1997-05-28",
    "frequency": "분기",
    "group": "MJSD"
  },
  {
    "symbol": "ARKB",
    "market": "NYSE",
    "currency": "USD",
    "company": "ARK"
  },
  {
    "symbol": "ARKF",
    "market": "NYSE",
    "currency": "USD",
    "company": "ARK"
  },
  {
    "symbol": "ARKG",
    "market": "NYSE",
    "currency": "USD",
    "company": "ARK"
  },
  {
    "symbol": "ARKQ",
    "market": "NYSE",
    "currency": "USD",
    "company": "ARK"
  },
  {
    "symbol": "ARKW",
    "market": "NYSE",
    "currency": "USD",
    "company": "ARK"
  },
  {
    "symbol": "ARTY",
    "market": "NYSE",
    "currency": "USD",
    "company": "iShares"
  },
  {
    "symbol": "ASHR",
    "market": "NYSE",
    "currency": "USD",
    "company": "Xtrackers"
  },
  {
    "symbol": "ATO",
    "market": "NYSE",
    "currency": "USD",
    "ipoDate": "1983-12-28",
    "frequency": "분기",
    "group": "FMAN"
  },
  {
    "symbol": "AVB",
    "market": "NYSE",
    "currency": "USD",
    "ipoDate": "1994-03-11",
    "frequency": "분기",
    "group": "MJSD"
  },
  {
    "symbol": "AVDE",
    "market": "NYSE",
    "currency": "USD",
    "company": "Avantis"
  },
  {
    "symbol": "AVDV",
    "market": "NYSE",
    "currency": "USD",
    "company": "Avantis"
  },
  {
    "symbol": "AVEM",
    "market": "NYSE",
    "currency": "USD",
    "company": "Avantis"
  },
  {
    "symbol": "AVES",
    "market": "NYSE",
    "currency": "USD",
    "company": "Avantis"
  },
  {
    "symbol": "AVIG",
    "market": "NYSE",
    "currency": "USD",
    "company": "Avantis"
  },
  {
    "symbol": "AVIV",
    "market": "NYSE",
    "currency": "USD",
    "company": "Avantis"
  },
  {
    "symbol": "AVLC",
    "market": "NYSE",
    "currency": "USD",
    "company": "Avantis"
  },
  {
    "symbol": "AVLV",
    "market": "NYSE",
    "currency": "USD",
    "company": "Avantis"
  },
  {
    "symbol": "AVSC",
    "market": "NYSE",
    "currency": "USD",
    "company": "Avantis"
  },
  {
    "symbol": "AVUS",
    "market": "NYSE",
    "currency": "USD",
    "company": "Avantis"
  },
  {
    "symbol": "AVUV",
    "market": "NYSE",
    "currency": "USD",
    "company": "Avantis"
  },
  {
    "symbol": "AVY",
    "market": "NYSE",
    "currency": "USD",
    "ipoDate": "1973-02-21",
    "frequency": "분기",
    "group": "MJSD"
  },
  {
    "symbol": "AWK",
    "market": "NYSE",
    "currency": "USD",
    "ipoDate": "2008-04-23",
    "frequency": "분기",
    "group": "FMAN"
  },
  {
    "symbol": "AXP",
    "market": "NYSE",
    "currency": "USD",
    "ipoDate": "1972-06-01",
    "frequency": "분기",
    "group": "JAJO"
  },
  {
    "symbol": "AZO",
    "market": "NYSE",
    "currency": "USD",
    "ipoDate": "1991-04-02"
  }
]