[
    {
        "symbol": "D",
        "market": "NYSE",
        "currency": "USD",
        "ipoDate": "1980-03-17",
        "frequency": "분기",
        "group": "FMSN",
        "holdings": false
    },
    {
        "symbol": "DAL",
        "market": "NYSE",
        "currency": "USD",
        "ipoDate": "2007-05-03",
        "frequency": "분기",
        "group": "FMJO",
        "holdings": false
    },
    {
        "symbol": "DAY",
        "market": "NYSE",
        "currency": "USD",
        "ipoDate": "2018-04-26",
        "holdings": false
    },
    {
        "symbol": "DBA",
        "market": "NYSE",
        "currency": "USD",
        "company": "Invesco",
        "ipoDate": "2007-01-05",
        "frequency": "매년",
        "holdings": true
    },
    {
        "symbol": "DBC",
        "market": "NYSE",
        "currency": "USD",
        "company": "Invesco",
        "ipoDate": "2006-02-06",
        "frequency": "매년",
        "holdings": true
    },
    {
        "symbol": "DBEF",
        "market": "NYSE",
        "currency": "USD",
        "company": "Xtrackers",
        "ipoDate": "2011-06-09",
        "frequency": "매년",
        "holdings": true
    },
    {
        "symbol": "DBMF",
        "market": "NYSE",
        "currency": "USD",
        "company": "iMGP",
        "ipoDate": "2019-05-08",
        "frequency": "분기",
        "group": "MJSD",
        "holdings": false
    },
    {
        "symbol": "DCOR",
        "market": "NYSE",
        "currency": "USD",
        "company": "Dimensional",
        "ipoDate": "2023-09-13",
        "frequency": "분기",
        "group": "MJSD",
        "holdings": true
    },
    {
        "symbol": "DD",
        "market": "NYSE",
        "currency": "USD",
        "ipoDate": "1972-06-01",
        "frequency": "분기",
        "group": "MMAN",
        "holdings": false
    },
    {
        "symbol": "DDWM",
        "market": "NYSE",
        "currency": "USD",
        "company": "WisdomTree",
        "ipoDate": "2016-02-04",
        "frequency": "분기",
        "group": "MJSD",
        "holdings": true
    },
    {
        "symbol": "DE",
        "market": "NYSE",
        "currency": "USD",
        "ipoDate": "1972-06-01",
        "frequency": "분기",
        "group": "MJSD",
        "holdings": false
    },
    {
        "symbol": "DECK",
        "market": "NYSE",
        "currency": "USD",
        "ipoDate": "1993-10-15",
        "holdings": false
    },
    {
        "symbol": "DELL",
        "market": "NYSE",
        "currency": "USD",
        "ipoDate": "2016-08-17",
        "frequency": "분기",
        "group": "JAJO",
        "holdings": false
    },
    {
        "symbol": "DEM",
        "market": "NYSE",
        "currency": "USD",
        "company": "WisdomTree",
        "ipoDate": "2007-07-13",
        "frequency": "분기",
        "group": "MJSD",
        "holdings": true
    },
    {
        "symbol": "DES",
        "market": "NYSE",
        "currency": "USD",
        "company": "WisdomTree",
        "ipoDate": "2006-06-16",
        "frequency": "매월",
        "holdings": true
    },
    {
        "symbol": "DFAC",
        "market": "NYSE",
        "currency": "USD",
        "company": "Dimensional",
        "ipoDate": "2021-06-14",
        "frequency": "분기",
        "group": "MJSD",
        "holdings": true
    },
    {
        "symbol": "DFAE",
        "market": "NYSE",
        "currency": "USD",
        "company": "Dimensional",
        "ipoDate": "2020-12-03",
        "frequency": "분기",
        "group": "MJSD",
        "holdings": true
    },
    {
        "symbol": "DFAI",
        "market": "NYSE",
        "currency": "USD",
        "company": "Dimensional",
        "ipoDate": "2020-11-19",
        "frequency": "분기",
        "group": "MJSD",
        "holdings": true
    },
    {
        "symbol": "DFAR",
        "market": "NYSE",
        "currency": "USD",
        "company": "Dimensional",
        "ipoDate": "2022-02-24",
        "frequency": "분기",
        "group": "MJSD",
        "holdings": true
    },
    {
        "symbol": "DFAS",
        "market": "NYSE",
        "currency": "USD",
        "company": "Dimensional",
        "ipoDate": "2021-06-14",
        "frequency": "분기",
        "group": "MJSD",
        "holdings": true
    },
    {
        "symbol": "DFAT",
        "market": "NYSE",
        "currency": "USD",
        "company": "Dimensional",
        "ipoDate": "2021-06-14",
        "frequency": "분기",
        "group": "MJSD",
        "holdings": true
    },
    {
        "symbol": "DFAU",
        "market": "NYSE",
        "currency": "USD",
        "company": "Dimensional",
        "ipoDate": "2020-11-19",
        "frequency": "분기",
        "group": "MJSD",
        "holdings": true
    },
    {
        "symbol": "DFAW",
        "market": "NYSE",
        "currency": "USD",
        "company": "Dimensional",
        "ipoDate": "2023-09-27",
        "frequency": "분기",
        "group": "MJSD",
        "holdings": true
    },
    {
        "symbol": "DFAX",
        "market": "NYSE",
        "currency": "USD",
        "company": "Dimensional",
        "ipoDate": "2021-09-13",
        "frequency": "분기",
        "group": "MJSD",
        "holdings": true
    },
    {
        "symbol": "DFCF",
        "market": "NYSE",
        "currency": "USD",
        "company": "Dimensional",
        "ipoDate": "2021-11-16",
        "frequency": "매월",
        "holdings": false
    },
    {
        "symbol": "DFEM",
        "market": "NYSE",
        "currency": "USD",
        "company": "Dimensional",
        "ipoDate": "2022-04-27",
        "frequency": "분기",
        "group": "MJSD",
        "holdings": true
    },
    {
        "symbol": "DFEV",
        "market": "NYSE",
        "currency": "USD",
        "company": "Dimensional",
        "ipoDate": "2022-04-27",
        "frequency": "분기",
        "group": "MJSD",
        "holdings": true
    },
    {
        "symbol": "DFGP",
        "market": "NYSE",
        "currency": "USD",
        "company": "Dimensional",
        "ipoDate": "2023-11-08",
        "frequency": "매월",
        "holdings": false
    },
    {
        "symbol": "DFGR",
        "market": "NYSE",
        "currency": "USD",
        "company": "Dimensional",
        "ipoDate": "2022-12-07",
        "frequency": "분기",
        "group": "MJSD",
        "holdings": true
    },
    {
        "symbol": "DFGX",
        "market": "NYSE",
        "currency": "USD",
        "company": "Dimensional",
        "ipoDate": "2023-11-08",
        "frequency": "매월",
        "holdings": false
    },
    {
        "symbol": "DFIC",
        "market": "NYSE",
        "currency": "USD",
        "company": "Dimensional",
        "ipoDate": "2022-03-24",
        "frequency": "분기",
        "group": "MJSD",
        "holdings": true
    },
    {
        "symbol": "DFIP",
        "market": "NYSE",
        "currency": "USD",
        "company": "Dimensional",
        "ipoDate": "2021-11-16",
        "frequency": "매월",
        "holdings": false
    },
    {
        "symbol": "DFIS",
        "market": "NYSE",
        "currency": "USD",
        "company": "Dimensional",
        "ipoDate": "2022-03-24",
        "frequency": "분기",
        "group": "MJSD",
        "holdings": true
    },
    {
        "symbol": "DFIV",
        "market": "NYSE",
        "currency": "USD",
        "company": "Dimensional",
        "ipoDate": "2021-09-13",
        "frequency": "분기",
        "group": "MJSD",
        "holdings": true
    },
    {
        "symbol": "DFLV",
        "market": "NYSE",
        "currency": "USD",
        "company": "Dimensional",
        "ipoDate": "2022-12-07",
        "frequency": "분기",
        "group": "MJSD",
        "holdings": true
    },
    {
        "symbol": "DFNM",
        "market": "NYSE",
        "currency": "USD",
        "company": "Dimensional",
        "ipoDate": "2021-11-16",
        "frequency": "매월",
        "holdings": false
    },
    {
        "symbol": "DFSD",
        "market": "NYSE",
        "currency": "USD",
        "company": "Dimensional",
        "ipoDate": "2021-11-16",
        "frequency": "매월",
        "holdings": false
    },
    {
        "symbol": "DFSI",
        "market": "NYSE",
        "currency": "USD",
        "company": "Dimensional",
        "ipoDate": "2022-11-02",
        "frequency": "분기",
        "group": "MJSD",
        "holdings": true
    },
    {
        "symbol": "DFSU",
        "market": "NYSE",
        "currency": "USD",
        "company": "Dimensional",
        "ipoDate": "2022-11-02",
        "frequency": "분기",
        "group": "MJSD",
        "holdings": true
    },
    {
        "symbol": "DFSV",
        "market": "NYSE",
        "currency": "USD",
        "company": "Dimensional",
        "ipoDate": "2022-02-24",
        "frequency": "분기",
        "group": "MJSD",
        "holdings": true
    },
    {
        "symbol": "DFUS",
        "market": "NYSE",
        "currency": "USD",
        "company": "Dimensional",
        "ipoDate": "2021-06-14",
        "frequency": "분기",
        "group": "MJSD",
        "holdings": true
    },
    {
        "symbol": "DFUV",
        "market": "NYSE",
        "currency": "USD",
        "company": "Dimensional",
        "ipoDate": "2022-05-09",
        "frequency": "분기",
        "group": "MJSD",
        "holdings": true
    },
    {
        "symbol": "DG",
        "market": "NYSE",
        "currency": "USD",
        "ipoDate": "2009-11-13",
        "frequency": "분기",
        "group": "JAJO",
        "holdings": false
    },
    {
        "symbol": "DGRO",
        "company": "iShares",
        "frequency": "분기",
        "group": "MJSD",
        "ipoDate": "2014-06-12",
        "market": "NYSE",
        "holdings": true
    },
    {
        "symbol": "DGS",
        "market": "NYSE",
        "currency": "USD",
        "company": "WisdomTree",
        "ipoDate": "2007-10-30",
        "frequency": "분기",
        "group": "MJSD",
        "holdings": true
    },
    {
        "symbol": "DGX",
        "market": "NYSE",
        "currency": "USD",
        "ipoDate": "1996-12-17",
        "frequency": "분기",
        "group": "JAJO",
        "holdings": false
    },
    {
        "symbol": "DHI",
        "market": "NYSE",
        "currency": "USD",
        "ipoDate": "1992-06-05",
        "frequency": "분기",
        "group": "FMAN",
        "holdings": false
    },
    {
        "symbol": "DHR",
        "market": "NYSE",
        "currency": "USD",
        "ipoDate": "1978-12-29",
        "frequency": "분기",
        "group": "MJSD",
        "holdings": false
    },
    {
        "symbol": "DHS",
        "market": "NYSE",
        "currency": "USD",
        "company": "WisdomTree",
        "ipoDate": "2006-06-16",
        "frequency": "매월",
        "holdings": true
    },
    {
        "symbol": "DIA",
        "company": "SPDR",
        "frequency": "매월",
        "ipoDate": "1998-01-20",
        "market": "NYSE",
        "holdings": true
    },
    {
        "symbol": "DIHP",
        "market": "NYSE",
        "currency": "USD",
        "company": "Dimensional",
        "ipoDate": "2022-03-24",
        "frequency": "분기",
        "group": "MJSD",
        "holdings": true
    },
    {
        "symbol": "DIPS",
        "company": "YieldMax",
        "frequency": "매주",
        "group": "목",
        "underlying": "NVDA",
        "ipoDate": "2024-07-24",
        "market": "NYSE",
        "holdings": true
    },
    {
        "symbol": "DIS",
        "ipoDate": "1962-01-02",
        "market": "NYSE",
        "frequency": "분기",
        "group": "MSND",
        "holdings": false
    },
    {
        "symbol": "DISO",
        "company": "YieldMax",
        "frequency": "매주",
        "group": "목",
        "underlying": "DIS",
        "ipoDate": "2023-08-25",
        "market": "NYSE",
        "holdings": true
    },
    {
        "symbol": "DISV",
        "market": "NYSE",
        "currency": "USD",
        "company": "Dimensional",
        "ipoDate": "2022-03-24",
        "frequency": "분기",
        "group": "MJSD",
        "holdings": true
    },
    {
        "symbol": "DIVB",
        "market": "NYSE",
        "currency": "USD",
        "company": "iShares",
        "ipoDate": "2017-11-09",
        "frequency": "분기",
        "group": "MJSD",
        "holdings": true
    },
    {
        "symbol": "DIVI",
        "market": "NYSE",
        "currency": "USD",
        "company": "Franklin",
        "ipoDate": "2016-06-03",
        "frequency": "분기",
        "group": "MJSD",
        "holdings": true
    },
    {
        "symbol": "DIVO",
        "company": "Amplify",
        "frequency": "매월",
        "ipoDate": "2016-12-15",
        "market": "NYSE",
        "holdings": true
    },
    {
        "symbol": "DLN",
        "market": "NYSE",
        "currency": "USD",
        "company": "WisdomTree",
        "ipoDate": "2006-06-16",
        "frequency": "매월",
        "holdings": true
    },
    {
        "symbol": "DLR",
        "market": "NYSE",
        "currency": "USD",
        "ipoDate": "2004-10-29",
        "frequency": "분기",
        "group": "MJSD",
        "holdings": false
    },
    {
        "symbol": "DLS",
        "market": "NYSE",
        "currency": "USD",
        "company": "WisdomTree",
        "ipoDate": "2006-06-16",
        "frequency": "분기",
        "group": "MJSD",
        "holdings": true
    },
    {
        "symbol": "DOC",
        "market": "NYSE",
        "currency": "USD",
        "ipoDate": "1985-05-23",
        "frequency": "매월",
        "holdings": false
    },
    {
        "symbol": "DON",
        "market": "NYSE",
        "currency": "USD",
        "company": "WisdomTree",
        "ipoDate": "2006-06-16",
        "frequency": "매월",
        "holdings": true
    },
    {
        "symbol": "DOV",
        "market": "NYSE",
        "currency": "USD",
        "ipoDate": "1980-03-17",
        "frequency": "분기",
        "group": "FMAN",
        "holdings": false
    },
    {
        "symbol": "DOW",
        "market": "NYSE",
        "currency": "USD",
        "ipoDate": "2019-03-20",
        "frequency": "분기",
        "group": "FMAN",
        "holdings": false
    },
    {
        "symbol": "DRAY",
        "company": "YieldMax",
        "frequency": "매주",
        "group": "목",
        "underlying": "DKNG",
        "ipoDate": "2025-07-15",
        "market": "NYSE",
        "holdings": true
    },
    {
        "symbol": "DRI",
        "market": "NYSE",
        "currency": "USD",
        "ipoDate": "1995-05-09",
        "frequency": "분기",
        "group": "JAJO",
        "holdings": false
    },
    {
        "symbol": "DRSK",
        "market": "NYSE",
        "currency": "USD",
        "company": "Aptus",
        "ipoDate": "2018-08-09",
        "frequency": "분기",
        "group": "MJSD",
        "holdings": true
    },
    {
        "symbol": "DSI",
        "market": "NYSE",
        "currency": "USD",
        "company": "iShares",
        "ipoDate": "2006-11-17",
        "frequency": "분기",
        "group": "MJSD",
        "holdings": true
    },
    {
        "symbol": "DSTL",
        "market": "NYSE",
        "currency": "USD",
        "company": "Distillate",
        "ipoDate": "2018-10-24",
        "frequency": "분기",
        "group": "MJSD",
        "holdings": true
    },
    {
        "symbol": "DTD",
        "market": "NYSE",
        "currency": "USD",
        "company": "WisdomTree",
        "ipoDate": "2006-06-16",
        "frequency": "매월",
        "holdings": true
    },
    {
        "symbol": "DTE",
        "market": "NYSE",
        "currency": "USD",
        "ipoDate": "1962-01-02",
        "frequency": "분기",
        "group": "MJSD",
        "holdings": false
    },
    {
        "symbol": "DUHP",
        "market": "NYSE",
        "currency": "USD",
        "company": "Dimensional",
        "ipoDate": "2022-02-24",
        "frequency": "분기",
        "group": "MJSD",
        "holdings": true
    },
    {
        "symbol": "DUK",
        "market": "NYSE",
        "currency": "USD",
        "ipoDate": "1980-03-17",
        "frequency": "분기",
        "group": "FMAN",
        "holdings": false
    },
    {
        "symbol": "DUSA",
        "market": "NYSE",
        "currency": "USD",
        "company": "Davis",
        "ipoDate": "2017-01-12",
        "frequency": "매년",
        "holdings": true
    },
    {
        "symbol": "DUSB",
        "market": "NYSE",
        "currency": "USD",
        "company": "Dimensional",
        "ipoDate": "2023-09-27",
        "frequency": "매월",
        "holdings": false
    },
    {
        "symbol": "DVA",
        "market": "NYSE",
        "currency": "USD",
        "ipoDate": "1995-10-31",
        "holdings": false
    },
    {
        "symbol": "DVN",
        "market": "NYSE",
        "currency": "USD",
        "ipoDate": "1985-07-22",
        "frequency": "분기",
        "group": "MJSD",
        "holdings": false
    },
    {
        "symbol": "DVY",
        "market": "NYSE",
        "currency": "USD",
        "company": "iShares",
        "ipoDate": "2003-11-07",
        "frequency": "분기",
        "group": "MJSD",
        "holdings": true
    },
    {
        "symbol": "DVYE",
        "market": "NYSE",
        "currency": "USD",
        "company": "iShares",
        "ipoDate": "2012-02-24",
        "frequency": "분기",
        "group": "MJSD",
        "holdings": true
    },
    {
        "symbol": "DXJ",
        "market": "NYSE",
        "currency": "USD",
        "company": "WisdomTree",
        "ipoDate": "2006-06-16",
        "frequency": "분기",
        "holdings": true
    },
    {
        "symbol": "DYNF",
        "market": "NYSE",
        "currency": "USD",
        "company": "iShares",
        "ipoDate": "2019-03-21",
        "frequency": "분기",
        "group": "MJSD",
        "holdings": true
    }
]
